ehrax/__init__.py
ehrax/_literals.py
ehrax/base.py
ehrax/coding_scheme.py
ehrax/dataset.py
ehrax/freezer.py
ehrax/transformations.py
ehrax/tvx_concepts.py
ehrax/tvx_ehr.py
ehrax/tvx_transformations.py
ehrax/utils.py
ehrax/.idea/.gitignore
ehrax/.idea/ehrax.iml
ehrax/.idea/misc.xml
ehrax/.idea/modules.xml
ehrax/.idea/vcs.xml
ehrax/.idea/workspace.xml
ehrax/.idea/inspectionProfiles/Project_Default.xml
ehrax/.idea/inspectionProfiles/profiles_settings.xml
ehrax/.idea/stats/__init__.py
ehrax/_stats/__init__.py
ehrax/_stats/coding_scheme.py
ehrax/_stats/dataset.py
ehrax/example_datasets/__init__.py
ehrax/example_datasets/cprd.py
ehrax/example_datasets/mimic.py
ehrax/example_datasets/mimic_in_memory.py
ehrax/example_datasets/mimic_sql.py
ehrax/example_datasets/study_mimic_aki.py
ehrax/example_datasets/study_mimic_dx_summary.py
ehrax/example_schemes/__init__.py
ehrax/example_schemes/ccs.py
ehrax/example_schemes/cprd.py
ehrax/example_schemes/icd.py
ehrax/example_schemes/icd10.py
ehrax/example_schemes/icd9.py
ehrax/example_schemes/icd_ccs_integration.py
ehrax/example_schemes/literals.py
ehrax/example_schemes/mixed_icd.py
ehrax/example_schemes/snomed.py
ehrax/resources/CCS/$dxref 2015.csv.gz
ehrax/resources/CCS/$prref 2015.csv.gz
ehrax/resources/CCS/README.md
ehrax/resources/CCS/ccs_dx_icd10cm_2019_1.csv.gz
ehrax/resources/CCS/ccs_multi_dx_tool_2015.csv.gz
ehrax/resources/CCS/ccs_multi_pr_tool_2015.csv.gz
ehrax/resources/CCS/ccs_pr_icd10pcs_2020_1.csv.gz
ehrax/resources/CCS/dxlabel 2015.csv.gz
ehrax/resources/CCS/dxmlabel-13.csv.gz
ehrax/resources/CCS/prlabel 2014.csv.gz
ehrax/resources/CCS/prmlabel-09.csv.gz
ehrax/resources/CPRD/CPRD_212_LTC_ALL.csv.gz
ehrax/resources/CPRD/cprd_eth.csv
ehrax/resources/ICD/2018_gem_cm_I10I9.txt.gz
ehrax/resources/ICD/2018_gem_cm_I9I10.txt.gz
ehrax/resources/ICD/2018_gem_pcs_I10I9.txt.gz
ehrax/resources/ICD/2018_gem_pcs_I9I10.txt.gz
ehrax/resources/ICD/HOM-ICD9.csv.gz
ehrax/resources/ICD/ICD9CM.csv.gz
ehrax/resources/ICD/README.md
ehrax-2025.9.22.dist-info/METADATA
ehrax-2025.9.22.dist-info/WHEEL
ehrax-2025.9.22.dist-info/licenses/LICENCE
ehrax-2025.9.22.dist-info/RECORD
